{
	"John Kasich": {
		"id_str":"721858119077339008",
		"timestamp":"4/18/2016 12:29:00 AM",
		"sentiment":"{\"0\":{\"Token\":{\"Come\":{\"Lemma\":\"come\",\"CharacterOffsetBegin\":40,\"PartOfSpeech\":\"VB\",\"NamedEntityTag\":\"O\",\"CharacterOffsetEnd\":44,\"Sentiment\":\"Neutral\"},\"'s\":{\"Lemma\":\"'s\",\"CharacterOffsetBegin\":8,\"PartOfSpeech\":\"POS\",\"NamedEntityTag\":\"O\",\"CharacterOffsetEnd\":10,\"Sentiment\":\"Neutral\"},\"An\":{\"Lemma\":\"a\",\"CharacterOffsetBegin\":25,\"PartOfSpeech\":\"DT\",\"NamedEntityTag\":\"O\",\"CharacterOffsetEnd\":27,\"Sentiment\":\"Neutral\"},\"via\":{\"Lemma\":\"via\",\"CharacterOffsetBegin\":77,\"PartOfSpeech\":\"IN\",\"NamedEntityTag\":\"O\",\"CharacterOffsetEnd\":80,\"Sentiment\":\"Neutral\"},\"@TPM\":{\"Lemma\":\"@tpm\",\"CharacterOffsetBegin\":81,\"PartOfSpeech\":\"NN\",\"NamedEntityTag\":\"O\",\"CharacterOffsetEnd\":85,\"Sentiment\":\"Neutral\"},\"https:\/\/t.co\/jB6KQuySNz\":{\"Lemma\":\"https:\/\/t.co\/jb6kquysnz\",\"CharacterOffsetBegin\":53,\"PartOfSpeech\":\"NN\",\"NamedEntityTag\":\"O\",\"CharacterOffsetEnd\":76,\"Sentiment\":\"Neutral\"},\"Ted\":{\"Lemma\":\"Ted\",\"CharacterOffsetBegin\":0,\"PartOfSpeech\":\"NNP\",\"NamedEntityTag\":\"PERSON\",\"CharacterOffsetEnd\":3,\"Sentiment\":\"Neutral\"},\"U.S.\":{\"Lemma\":\"U.S.\",\"CharacterOffsetBegin\":48,\"PartOfSpeech\":\"NNP\",\"NamedEntityTag\":\"LOCATION\",\"CharacterOffsetEnd\":52,\"Sentiment\":\"Neutral\"},\"Cruz\":{\"Lemma\":\"Cruz\",\"CharacterOffsetBegin\":4,\"PartOfSpeech\":\"NNP\",\"NamedEntityTag\":\"PERSON\",\"CharacterOffsetEnd\":8,\"Sentiment\":\"Neutral\"},\"Official\":{\"Lemma\":\"Official\",\"CharacterOffsetBegin\":28,\"PartOfSpeech\":\"NNP\",\"NamedEntityTag\":\"O\",\"CharacterOffsetEnd\":36,\"Sentiment\":\"Neutral\"},\"To\":{\"Lemma\":\"to\",\"CharacterOffsetBegin\":45,\"PartOfSpeech\":\"TO\",\"NamedEntityTag\":\"O\",\"CharacterOffsetEnd\":47,\"Sentiment\":\"Neutral\"},\"Father\":{\"Lemma\":\"Father\",\"CharacterOffsetBegin\":11,\"PartOfSpeech\":\"NNP\",\"NamedEntityTag\":\"O\",\"CharacterOffsetEnd\":17,\"Sentiment\":\"Neutral\"},\"Bribed\":{\"Lemma\":\"Bribed\",\"CharacterOffsetBegin\":18,\"PartOfSpeech\":\"NNP\",\"NamedEntityTag\":\"O\",\"CharacterOffsetEnd\":24,\"Sentiment\":\"Neutral\"}},\"Dependency\":{\"clausal modifier of noun\":{\"dev\":\"Come\",\"gov\":\"Bribed\"},\"nmod_preposition\":{\"dev\":\"@TPM\",\"gov\":\"Bribed\"},\"marker\":{\"dev\":\"To\",\"gov\":\"Come\"},\"possession modifier\":{\"dev\":\"Cruz\",\"gov\":\"Bribed\"},\"case marker\":{\"dev\":\"via\",\"gov\":\"@TPM\"},\"root\":{\"dev\":\"Bribed\",\"gov\":\"\"},\"determiner\":{\"dev\":\"An\",\"gov\":\"Official\"},\"nominal subject\":{\"dev\":\"Official\",\"gov\":\"Come\"},\"compound modifier\":{\"dev\":\"U.S.\",\"gov\":\"https:\/\/t.co\/jB6KQuySNz\"}}},\"Sentiment\":-1}",
		"tweet_name":"Mark allen jobe",
		"tweet_text":"Ted Cruz's Father Bribed An Official To Come To U.S. https://t.co/jB6KQuySNz via @TPM",
		"tweet_user_id":"Markallenjobe1"
	},

	"Ted Cruz": {
		"id_str":"721858119077339008",
		"timestamp":"4/18/2016 12:29:00 AM",
		"sentiment":"{\"0\":{\"Token\":{\"Come\":{\"Lemma\":\"come\",\"CharacterOffsetBegin\":40,\"PartOfSpeech\":\"VB\",\"NamedEntityTag\":\"O\",\"CharacterOffsetEnd\":44,\"Sentiment\":\"Neutral\"},\"'s\":{\"Lemma\":\"'s\",\"CharacterOffsetBegin\":8,\"PartOfSpeech\":\"POS\",\"NamedEntityTag\":\"O\",\"CharacterOffsetEnd\":10,\"Sentiment\":\"Neutral\"},\"An\":{\"Lemma\":\"a\",\"CharacterOffsetBegin\":25,\"PartOfSpeech\":\"DT\",\"NamedEntityTag\":\"O\",\"CharacterOffsetEnd\":27,\"Sentiment\":\"Neutral\"},\"via\":{\"Lemma\":\"via\",\"CharacterOffsetBegin\":77,\"PartOfSpeech\":\"IN\",\"NamedEntityTag\":\"O\",\"CharacterOffsetEnd\":80,\"Sentiment\":\"Neutral\"},\"@TPM\":{\"Lemma\":\"@tpm\",\"CharacterOffsetBegin\":81,\"PartOfSpeech\":\"NN\",\"NamedEntityTag\":\"O\",\"CharacterOffsetEnd\":85,\"Sentiment\":\"Neutral\"},\"https:\/\/t.co\/jB6KQuySNz\":{\"Lemma\":\"https:\/\/t.co\/jb6kquysnz\",\"CharacterOffsetBegin\":53,\"PartOfSpeech\":\"NN\",\"NamedEntityTag\":\"O\",\"CharacterOffsetEnd\":76,\"Sentiment\":\"Neutral\"},\"Ted\":{\"Lemma\":\"Ted\",\"CharacterOffsetBegin\":0,\"PartOfSpeech\":\"NNP\",\"NamedEntityTag\":\"PERSON\",\"CharacterOffsetEnd\":3,\"Sentiment\":\"Neutral\"},\"U.S.\":{\"Lemma\":\"U.S.\",\"CharacterOffsetBegin\":48,\"PartOfSpeech\":\"NNP\",\"NamedEntityTag\":\"LOCATION\",\"CharacterOffsetEnd\":52,\"Sentiment\":\"Neutral\"},\"Cruz\":{\"Lemma\":\"Cruz\",\"CharacterOffsetBegin\":4,\"PartOfSpeech\":\"NNP\",\"NamedEntityTag\":\"PERSON\",\"CharacterOffsetEnd\":8,\"Sentiment\":\"Neutral\"},\"Official\":{\"Lemma\":\"Official\",\"CharacterOffsetBegin\":28,\"PartOfSpeech\":\"NNP\",\"NamedEntityTag\":\"O\",\"CharacterOffsetEnd\":36,\"Sentiment\":\"Neutral\"},\"To\":{\"Lemma\":\"to\",\"CharacterOffsetBegin\":45,\"PartOfSpeech\":\"TO\",\"NamedEntityTag\":\"O\",\"CharacterOffsetEnd\":47,\"Sentiment\":\"Neutral\"},\"Father\":{\"Lemma\":\"Father\",\"CharacterOffsetBegin\":11,\"PartOfSpeech\":\"NNP\",\"NamedEntityTag\":\"O\",\"CharacterOffsetEnd\":17,\"Sentiment\":\"Neutral\"},\"Bribed\":{\"Lemma\":\"Bribed\",\"CharacterOffsetBegin\":18,\"PartOfSpeech\":\"NNP\",\"NamedEntityTag\":\"O\",\"CharacterOffsetEnd\":24,\"Sentiment\":\"Neutral\"}},\"Dependency\":{\"clausal modifier of noun\":{\"dev\":\"Come\",\"gov\":\"Bribed\"},\"nmod_preposition\":{\"dev\":\"@TPM\",\"gov\":\"Bribed\"},\"marker\":{\"dev\":\"To\",\"gov\":\"Come\"},\"possession modifier\":{\"dev\":\"Cruz\",\"gov\":\"Bribed\"},\"case marker\":{\"dev\":\"via\",\"gov\":\"@TPM\"},\"root\":{\"dev\":\"Bribed\",\"gov\":\"\"},\"determiner\":{\"dev\":\"An\",\"gov\":\"Official\"},\"nominal subject\":{\"dev\":\"Official\",\"gov\":\"Come\"},\"compound modifier\":{\"dev\":\"U.S.\",\"gov\":\"https:\/\/t.co\/jB6KQuySNz\"}}},\"Sentiment\":-1}",
		"tweet_name":"Mark allen jobe",
		"tweet_text":"Ted Cruz's Father Bribed An Official To Come To U.S. https://t.co/jB6KQuySNz via @TPM",
		"tweet_user_id":"Markallenjobe1"
	},

	"Donald Trump": {
		"id_str":"721858119077339008",
		"timestamp":"4/18/2016 12:29:00 AM",
		"sentiment":"{\"0\":{\"Token\":{\"Come\":{\"Lemma\":\"come\",\"CharacterOffsetBegin\":40,\"PartOfSpeech\":\"VB\",\"NamedEntityTag\":\"O\",\"CharacterOffsetEnd\":44,\"Sentiment\":\"Neutral\"},\"'s\":{\"Lemma\":\"'s\",\"CharacterOffsetBegin\":8,\"PartOfSpeech\":\"POS\",\"NamedEntityTag\":\"O\",\"CharacterOffsetEnd\":10,\"Sentiment\":\"Neutral\"},\"An\":{\"Lemma\":\"a\",\"CharacterOffsetBegin\":25,\"PartOfSpeech\":\"DT\",\"NamedEntityTag\":\"O\",\"CharacterOffsetEnd\":27,\"Sentiment\":\"Neutral\"},\"via\":{\"Lemma\":\"via\",\"CharacterOffsetBegin\":77,\"PartOfSpeech\":\"IN\",\"NamedEntityTag\":\"O\",\"CharacterOffsetEnd\":80,\"Sentiment\":\"Neutral\"},\"@TPM\":{\"Lemma\":\"@tpm\",\"CharacterOffsetBegin\":81,\"PartOfSpeech\":\"NN\",\"NamedEntityTag\":\"O\",\"CharacterOffsetEnd\":85,\"Sentiment\":\"Neutral\"},\"https:\/\/t.co\/jB6KQuySNz\":{\"Lemma\":\"https:\/\/t.co\/jb6kquysnz\",\"CharacterOffsetBegin\":53,\"PartOfSpeech\":\"NN\",\"NamedEntityTag\":\"O\",\"CharacterOffsetEnd\":76,\"Sentiment\":\"Neutral\"},\"Ted\":{\"Lemma\":\"Ted\",\"CharacterOffsetBegin\":0,\"PartOfSpeech\":\"NNP\",\"NamedEntityTag\":\"PERSON\",\"CharacterOffsetEnd\":3,\"Sentiment\":\"Neutral\"},\"U.S.\":{\"Lemma\":\"U.S.\",\"CharacterOffsetBegin\":48,\"PartOfSpeech\":\"NNP\",\"NamedEntityTag\":\"LOCATION\",\"CharacterOffsetEnd\":52,\"Sentiment\":\"Neutral\"},\"Cruz\":{\"Lemma\":\"Cruz\",\"CharacterOffsetBegin\":4,\"PartOfSpeech\":\"NNP\",\"NamedEntityTag\":\"PERSON\",\"CharacterOffsetEnd\":8,\"Sentiment\":\"Neutral\"},\"Official\":{\"Lemma\":\"Official\",\"CharacterOffsetBegin\":28,\"PartOfSpeech\":\"NNP\",\"NamedEntityTag\":\"O\",\"CharacterOffsetEnd\":36,\"Sentiment\":\"Neutral\"},\"To\":{\"Lemma\":\"to\",\"CharacterOffsetBegin\":45,\"PartOfSpeech\":\"TO\",\"NamedEntityTag\":\"O\",\"CharacterOffsetEnd\":47,\"Sentiment\":\"Neutral\"},\"Father\":{\"Lemma\":\"Father\",\"CharacterOffsetBegin\":11,\"PartOfSpeech\":\"NNP\",\"NamedEntityTag\":\"O\",\"CharacterOffsetEnd\":17,\"Sentiment\":\"Neutral\"},\"Bribed\":{\"Lemma\":\"Bribed\",\"CharacterOffsetBegin\":18,\"PartOfSpeech\":\"NNP\",\"NamedEntityTag\":\"O\",\"CharacterOffsetEnd\":24,\"Sentiment\":\"Neutral\"}},\"Dependency\":{\"clausal modifier of noun\":{\"dev\":\"Come\",\"gov\":\"Bribed\"},\"nmod_preposition\":{\"dev\":\"@TPM\",\"gov\":\"Bribed\"},\"marker\":{\"dev\":\"To\",\"gov\":\"Come\"},\"possession modifier\":{\"dev\":\"Cruz\",\"gov\":\"Bribed\"},\"case marker\":{\"dev\":\"via\",\"gov\":\"@TPM\"},\"root\":{\"dev\":\"Bribed\",\"gov\":\"\"},\"determiner\":{\"dev\":\"An\",\"gov\":\"Official\"},\"nominal subject\":{\"dev\":\"Official\",\"gov\":\"Come\"},\"compound modifier\":{\"dev\":\"U.S.\",\"gov\":\"https:\/\/t.co\/jB6KQuySNz\"}}},\"Sentiment\":-1}",
		"tweet_name":"Mark allen jobe",
		"tweet_text":"Ted Cruz's Father Bribed An Official To Come To U.S. https://t.co/jB6KQuySNz via @TPM",
		"tweet_user_id":"Markallenjobe1"
	},

	"Bernie Sanders": {
		"id_str":"721858119077339008",
		"timestamp":"4/18/2016 12:29:00 AM",
		"sentiment":"{\"0\":{\"Token\":{\"Come\":{\"Lemma\":\"come\",\"CharacterOffsetBegin\":40,\"PartOfSpeech\":\"VB\",\"NamedEntityTag\":\"O\",\"CharacterOffsetEnd\":44,\"Sentiment\":\"Neutral\"},\"'s\":{\"Lemma\":\"'s\",\"CharacterOffsetBegin\":8,\"PartOfSpeech\":\"POS\",\"NamedEntityTag\":\"O\",\"CharacterOffsetEnd\":10,\"Sentiment\":\"Neutral\"},\"An\":{\"Lemma\":\"a\",\"CharacterOffsetBegin\":25,\"PartOfSpeech\":\"DT\",\"NamedEntityTag\":\"O\",\"CharacterOffsetEnd\":27,\"Sentiment\":\"Neutral\"},\"via\":{\"Lemma\":\"via\",\"CharacterOffsetBegin\":77,\"PartOfSpeech\":\"IN\",\"NamedEntityTag\":\"O\",\"CharacterOffsetEnd\":80,\"Sentiment\":\"Neutral\"},\"@TPM\":{\"Lemma\":\"@tpm\",\"CharacterOffsetBegin\":81,\"PartOfSpeech\":\"NN\",\"NamedEntityTag\":\"O\",\"CharacterOffsetEnd\":85,\"Sentiment\":\"Neutral\"},\"https:\/\/t.co\/jB6KQuySNz\":{\"Lemma\":\"https:\/\/t.co\/jb6kquysnz\",\"CharacterOffsetBegin\":53,\"PartOfSpeech\":\"NN\",\"NamedEntityTag\":\"O\",\"CharacterOffsetEnd\":76,\"Sentiment\":\"Neutral\"},\"Ted\":{\"Lemma\":\"Ted\",\"CharacterOffsetBegin\":0,\"PartOfSpeech\":\"NNP\",\"NamedEntityTag\":\"PERSON\",\"CharacterOffsetEnd\":3,\"Sentiment\":\"Neutral\"},\"U.S.\":{\"Lemma\":\"U.S.\",\"CharacterOffsetBegin\":48,\"PartOfSpeech\":\"NNP\",\"NamedEntityTag\":\"LOCATION\",\"CharacterOffsetEnd\":52,\"Sentiment\":\"Neutral\"},\"Cruz\":{\"Lemma\":\"Cruz\",\"CharacterOffsetBegin\":4,\"PartOfSpeech\":\"NNP\",\"NamedEntityTag\":\"PERSON\",\"CharacterOffsetEnd\":8,\"Sentiment\":\"Neutral\"},\"Official\":{\"Lemma\":\"Official\",\"CharacterOffsetBegin\":28,\"PartOfSpeech\":\"NNP\",\"NamedEntityTag\":\"O\",\"CharacterOffsetEnd\":36,\"Sentiment\":\"Neutral\"},\"To\":{\"Lemma\":\"to\",\"CharacterOffsetBegin\":45,\"PartOfSpeech\":\"TO\",\"NamedEntityTag\":\"O\",\"CharacterOffsetEnd\":47,\"Sentiment\":\"Neutral\"},\"Father\":{\"Lemma\":\"Father\",\"CharacterOffsetBegin\":11,\"PartOfSpeech\":\"NNP\",\"NamedEntityTag\":\"O\",\"CharacterOffsetEnd\":17,\"Sentiment\":\"Neutral\"},\"Bribed\":{\"Lemma\":\"Bribed\",\"CharacterOffsetBegin\":18,\"PartOfSpeech\":\"NNP\",\"NamedEntityTag\":\"O\",\"CharacterOffsetEnd\":24,\"Sentiment\":\"Neutral\"}},\"Dependency\":{\"clausal modifier of noun\":{\"dev\":\"Come\",\"gov\":\"Bribed\"},\"nmod_preposition\":{\"dev\":\"@TPM\",\"gov\":\"Bribed\"},\"marker\":{\"dev\":\"To\",\"gov\":\"Come\"},\"possession modifier\":{\"dev\":\"Cruz\",\"gov\":\"Bribed\"},\"case marker\":{\"dev\":\"via\",\"gov\":\"@TPM\"},\"root\":{\"dev\":\"Bribed\",\"gov\":\"\"},\"determiner\":{\"dev\":\"An\",\"gov\":\"Official\"},\"nominal subject\":{\"dev\":\"Official\",\"gov\":\"Come\"},\"compound modifier\":{\"dev\":\"U.S.\",\"gov\":\"https:\/\/t.co\/jB6KQuySNz\"}}},\"Sentiment\":-1}",
		"tweet_name":"Mark allen jobe",
		"tweet_text":"Ted Cruz's Father Bribed An Official To Come To U.S. https://t.co/jB6KQuySNz via @TPM",
		"tweet_user_id":"Markallenjobe1"
	},

	"Hillary Clinton": {
		"id_str":"721858119077339008",
		"timestamp":"4/18/2016 12:29:00 AM",
		"sentiment":"{\"0\":{\"Token\":{\"Come\":{\"Lemma\":\"come\",\"CharacterOffsetBegin\":40,\"PartOfSpeech\":\"VB\",\"NamedEntityTag\":\"O\",\"CharacterOffsetEnd\":44,\"Sentiment\":\"Neutral\"},\"'s\":{\"Lemma\":\"'s\",\"CharacterOffsetBegin\":8,\"PartOfSpeech\":\"POS\",\"NamedEntityTag\":\"O\",\"CharacterOffsetEnd\":10,\"Sentiment\":\"Neutral\"},\"An\":{\"Lemma\":\"a\",\"CharacterOffsetBegin\":25,\"PartOfSpeech\":\"DT\",\"NamedEntityTag\":\"O\",\"CharacterOffsetEnd\":27,\"Sentiment\":\"Neutral\"},\"via\":{\"Lemma\":\"via\",\"CharacterOffsetBegin\":77,\"PartOfSpeech\":\"IN\",\"NamedEntityTag\":\"O\",\"CharacterOffsetEnd\":80,\"Sentiment\":\"Neutral\"},\"@TPM\":{\"Lemma\":\"@tpm\",\"CharacterOffsetBegin\":81,\"PartOfSpeech\":\"NN\",\"NamedEntityTag\":\"O\",\"CharacterOffsetEnd\":85,\"Sentiment\":\"Neutral\"},\"https:\/\/t.co\/jB6KQuySNz\":{\"Lemma\":\"https:\/\/t.co\/jb6kquysnz\",\"CharacterOffsetBegin\":53,\"PartOfSpeech\":\"NN\",\"NamedEntityTag\":\"O\",\"CharacterOffsetEnd\":76,\"Sentiment\":\"Neutral\"},\"Ted\":{\"Lemma\":\"Ted\",\"CharacterOffsetBegin\":0,\"PartOfSpeech\":\"NNP\",\"NamedEntityTag\":\"PERSON\",\"CharacterOffsetEnd\":3,\"Sentiment\":\"Neutral\"},\"U.S.\":{\"Lemma\":\"U.S.\",\"CharacterOffsetBegin\":48,\"PartOfSpeech\":\"NNP\",\"NamedEntityTag\":\"LOCATION\",\"CharacterOffsetEnd\":52,\"Sentiment\":\"Neutral\"},\"Cruz\":{\"Lemma\":\"Cruz\",\"CharacterOffsetBegin\":4,\"PartOfSpeech\":\"NNP\",\"NamedEntityTag\":\"PERSON\",\"CharacterOffsetEnd\":8,\"Sentiment\":\"Neutral\"},\"Official\":{\"Lemma\":\"Official\",\"CharacterOffsetBegin\":28,\"PartOfSpeech\":\"NNP\",\"NamedEntityTag\":\"O\",\"CharacterOffsetEnd\":36,\"Sentiment\":\"Neutral\"},\"To\":{\"Lemma\":\"to\",\"CharacterOffsetBegin\":45,\"PartOfSpeech\":\"TO\",\"NamedEntityTag\":\"O\",\"CharacterOffsetEnd\":47,\"Sentiment\":\"Neutral\"},\"Father\":{\"Lemma\":\"Father\",\"CharacterOffsetBegin\":11,\"PartOfSpeech\":\"NNP\",\"NamedEntityTag\":\"O\",\"CharacterOffsetEnd\":17,\"Sentiment\":\"Neutral\"},\"Bribed\":{\"Lemma\":\"Bribed\",\"CharacterOffsetBegin\":18,\"PartOfSpeech\":\"NNP\",\"NamedEntityTag\":\"O\",\"CharacterOffsetEnd\":24,\"Sentiment\":\"Neutral\"}},\"Dependency\":{\"clausal modifier of noun\":{\"dev\":\"Come\",\"gov\":\"Bribed\"},\"nmod_preposition\":{\"dev\":\"@TPM\",\"gov\":\"Bribed\"},\"marker\":{\"dev\":\"To\",\"gov\":\"Come\"},\"possession modifier\":{\"dev\":\"Cruz\",\"gov\":\"Bribed\"},\"case marker\":{\"dev\":\"via\",\"gov\":\"@TPM\"},\"root\":{\"dev\":\"Bribed\",\"gov\":\"\"},\"determiner\":{\"dev\":\"An\",\"gov\":\"Official\"},\"nominal subject\":{\"dev\":\"Official\",\"gov\":\"Come\"},\"compound modifier\":{\"dev\":\"U.S.\",\"gov\":\"https:\/\/t.co\/jB6KQuySNz\"}}},\"Sentiment\":-1}",
		"tweet_name":"Mark allen jobe",
		"tweet_text":"Ted Cruz's Father Bribed An Official To Come To U.S. https://t.co/jB6KQuySNz via @TPM",
		"tweet_user_id":"Markallenjobe1"
	}
}