{
	"John Kasich": {
		"sentiment":33,
		"tweet_text":"turpis non felis mollis dignissim. Pellentesque eu nisl facilisis, feugiat diam sed, tempus tortor. Praesent pretium erat purus, nec ",
		"tweet_user_id":"ordinatescraper",
		"tweet_timestamp":"timestamp"
	},

	"Ted Cruz": {
		"sentiment":-3,
		"tweet_text":"Suspendisse id velit venenatis, elementum dolor eu, elementum ex. Cras id velit vehicula, venenatis nulla in, plac",
		"tweet_user_id":"ordinatescraper",
		"tweet_timestamp":"timestamp"
	},

	"Donald Trump": {
		"sentiment":-10,
		"tweet_text":"ondimentum laoreet elit, ac finibus nunc lacinia non. Duis congue volutpat cursus. Donec at nibh vel dui viverra effic",
		"tweet_user_id":"ordinatescraper",
		"tweet_timestamp":"timestamp"
	},

	"Bernie Sanders": {
		"sentiment":3.081081e+00,
		"tweet_text":"incidunt sollicitudin tellus, et hendrerit ipsum cursus sit amet. Aenean efficitur pulvinar se",
		"tweet_user_id":"ordinatescraper",
		"tweet_timestamp":"timestamp"
	},

	"Hillary Clinton": {
		"sentiment":-21,
		"tweet_text":"oreet, at aliquet est viverra. Vestibulum non orci turpis. Quisque in consequat purus, nec sodales dui. Pe",
		"tweet_user_id":"ordinatescraper",
		"tweet_timestamp":"timestamp"
	}
}